Metadata-Version: 2.1
Name: Ronaldo-cr7
Version: 0.0.1
Summary: this is a dumb package used for dumb calculation.
Home-page: UNKNOWN
Author: RISHI CHOWDARY
Author-email: rishi1718.peram@gmail.com
License: MIT
Platform: UNKNOWN
License-File: license.txt
